liquidsig/__init__.py
liquidsig/__main__.py
liquidsig/deconvolution.py
liquidsig/functions.py
liquidsig/py.typed
liquidsig-0.0.4.dist-info/LICENSE
liquidsig-0.0.4.dist-info/METADATA
liquidsig-0.0.4.dist-info/WHEEL
liquidsig-0.0.4.dist-info/entry_points.txt
liquidsig-0.0.4.dist-info/RECORD
