Metadata-Version: 2.3
Name: liquidsig
Version: 0.0.4
Summary: LiquidSig - cfRNA Deconvolution
License: MIT
Author: Nick Semenkovich
Author-email: semenko@alum.mit.edu
Requires-Python: >=3.10,<4.0
Classifier: Development Status :: 3 - Alpha
Classifier: License :: OSI Approved :: MIT License
Classifier: Programming Language :: Python :: 3
Classifier: Programming Language :: Python :: 3.10
Classifier: Programming Language :: Python :: 3.11
Classifier: Programming Language :: Python :: 3.12
Classifier: Programming Language :: Python :: 3.13
Requires-Dist: cellxgene-ontology-guide (>=1.3.1,<2.0.0)
Requires-Dist: click (>=8.0.1)
Requires-Dist: joblib (>=1.4.2,<2.0.0)
Requires-Dist: matplotlib (>=3.10.0,<4.0.0)
Requires-Dist: numpy (>=2.2.2,<3.0.0)
Requires-Dist: pandas (>=2.2.3,<3.0.0)
Requires-Dist: poetry (>=2.0.0,<3.0.0)
Requires-Dist: pyranges (>=0.1.2,<0.2.0)
Requires-Dist: scikit-learn (>=1.6.1,<2.0.0)
Requires-Dist: scipy (>=1.15.1,<2.0.0)
Requires-Dist: seaborn (>=0.13.2,<0.14.0)
Project-URL: Changelog, https://github.com/semenko/liquidsig/releases
Project-URL: Documentation, https://semenko.github.io/liquidsig
Project-URL: Homepage, https://github.com/semenko/liquidsig
Project-URL: Repository, https://github.com/semenko/liquidsig
